{
  "index": {
    "title": "Intro",
    "type": "page",
    "display": "hidden"
  },
  "sok": {
    "title": "Search",
    "type": "page",
    "theme": {
      "layout": "full"
    }
  },
  "hjelp": {
    "title": "Help",
    "type": "page"
  },
  "statistikk": {
    "title": "Statistics",
    "type": "page"
  },
  "om": {
    "title": "About",
    "type": "page"
  },
  "tilgjengelighetserklaring": {
    "type": "page",
    "display": "hidden"
  },
  "404": {
    "type": "page",
    "theme": {
      "timestamp": false,
      "typesetting": "article"
    }
  },
  "500": {
    "type": "page",
    "theme": {
      "timestamp": false,
      "typesetting": "article"
    }
  }
}