{
  "index": {
    "title": "Intro",
    "type": "page",
    "display": "hidden"
  },
  "sok": {
    "title": "Search",
    "type": "page",
    "href": "/sok?size=n_20_n&filters%5B0%5D%5Bfield%5D=fulltext_found.keyword&filters%5B0%5D%5Bvalues%5D%5B0%5D=true&filters%5B0%5D%5Btype%5D=all",
    "theme": {
      "layout": "full"
    }
  },
  "hjelp": {
    "title": "Help",
    "type": "page"
  },
  "sokestreng": {
    "title": "Search strings",
    "type": "page"
  },
  "statistikk": {
    "title": "Statistics",
    "type": "page"
  },
  "om": {
    "title": "About",
    "type": "page"
  },
  "tilgjengelighetserklaring": {
    "type": "page",
    "display": "hidden"
  },
  "404": {
    "type": "page",
    "theme": {
      "timestamp": false,
      "typesetting": "article"
    }
  },
  "500": {
    "type": "page",
    "theme": {
      "timestamp": false,
      "typesetting": "article"
    }
  }
}